slider_proj/__init__.py
slider_proj/settings.py
slider_task/__init__.py
slider_task/models.py
slider_task/pages.py
slider_task/static/slider_task/sliders.css
slider_task/static/slider_task/sliders.js
slider_task/templates/slider_task/SliderTaskPage.html
slider_task-0.1.1.dist-info/DESCRIPTION.rst
slider_task-0.1.1.dist-info/METADATA
slider_task-0.1.1.dist-info/RECORD
slider_task-0.1.1.dist-info/WHEEL
slider_task-0.1.1.dist-info/metadata.json
slider_task-0.1.1.dist-info/top_level.txt
