Metadata-Version: 2.0
Name: slider-task
Version: 0.1.1
Summary: oTree Slider Task.
Home-page: http://github.com/chkgk/slider_task
Author: Christian König genannt Kersting
Author-email: christian.koenig@awi.uni-heidelberg.de
License: MIT
Platform: UNKNOWN
